msa_handler/__init__.py
msa_handler/msa.py
msa_handler-0.1.0.dist-info/LICENSE
msa_handler-0.1.0.dist-info/METADATA
msa_handler-0.1.0.dist-info/WHEEL
msa_handler-0.1.0.dist-info/top_level.txt
msa_handler-0.1.0.dist-info/RECORD
