Metadata-Version: 2.1
Name: msa_handler
Version: 0.1.0
Summary: Tool for handling MSA files and mapping residue ids
Home-page: https://github.com/aminkvh
Author: Amin Akbari
Author-email: akbari.amin7@gmail.com
Classifier: Programming Language :: Python :: 3
Classifier: License :: OSI Approved :: MIT License
Classifier: Operating System :: OS Independent
Requires-Python: >=3.6
License-File: LICENSE
Requires-Dist: biopython
